Workbook

Sheet Overview
A1: WebriQ Central Hub v2.0 — Sprint Plan (All Phases)
A2: Companion to Specification v2.0 · 2-week sprint cadence (Sprint 0 is a 3-week infrastructure sprint) · Status rolls up live from the Sprint Plan sheet
A4: Phase | B4: Name | C4: Sprints | D4: Weeks | E4: Duration (wks) | F4: Goal | G4: Exit Condition | H4: Deliverables | I4: Done | J4: % Complete
A5: Phase 0 | B5: Infrastructure (0A + 0B) | C5: Sprints 0A–0B | D5: 1–4 | E5: 4 | F5: 0A: full v2.0 schema on existing v0.1 DB (§10.6 codebase mapping), auth + role RLS matrix. 0B: event bus, realtime, PWA shell, Resend, KB seed (D24 split). | G5: 0A: migrations green, existing flows still pass. 0B: dummy ticket -> processed event < 60s; shell installable on 3 platforms. | H5: =COUNTIF('Sprint Plan'!A:A,"Phase 0") | I5: =COUNTIFS('Sprint Plan'!A:A,"Phase 0",'Sprint Plan'!J:J,"Done") | J5: =IF(H5=0,0,I5/H5)
A6: Phase 1A | B6: PM + Desk Core | C6: Sprints 1–3 | D6: 5–10 | E6: 6 | F6: The team's daily work surface: onboarding, native projects/tasks/time, client desk, classification, dev dashboard. | G6: AC1 + AC3 demonstrated; team can run a real project natively. | H6: =COUNTIF('Sprint Plan'!A:A,"Phase 1A") | I6: =COUNTIFS('Sprint Plan'!A:A,"Phase 1A",'Sprint Plan'!J:J,"Done") | J6: =IF(H6=0,0,I6/H6)
A7: Phase 1B | B7: HR Core | C7: Sprints 4–5 | D7: 11–14 | E7: 4 | F7: Attendance, leaves, timesheets, announcements — full HR month can run natively. | G7: AC4 + AC5 demonstrated; HR sign-off on balances and derivation. | H7: =COUNTIF('Sprint Plan'!A:A,"Phase 1B") | I7: =COUNTIFS('Sprint Plan'!A:A,"Phase 1B",'Sprint Plan'!J:J,"Done") | J7: =IF(H7=0,0,I7/H7)
A8: Phase 1C | B8: AI Loop | C8: Sprints 6–8 | D8: 15–20 | E8: 6 | F8: Assessment, digest, plans, execution + StackShift publish flow, reply, KB seed, unified AI chat, MVP stats page. | G8: AC2 + AC6 + AC7 demonstrated; M14 stats live; hardening green. | H8: =COUNTIF('Sprint Plan'!A:A,"Phase 1C") | I8: =COUNTIFS('Sprint Plan'!A:A,"Phase 1C",'Sprint Plan'!J:J,"Done") | J8: =IF(H8=0,0,I8/H8)
A9: Phase 1D | B9: Migration & Cutover | C9: Sprint 9 | D9: 21–22 | E9: 2 | F9: Module-by-module Zoho cutover (HR -> Desk -> Projects), training, MVP exit. | G9: All AC1–AC6 met; Zoho read-only; MVP exit sign-off. | H9: =COUNTIF('Sprint Plan'!A:A,"Phase 1D") | I9: =COUNTIFS('Sprint Plan'!A:A,"Phase 1D",'Sprint Plan'!J:J,"Done") | J9: =IF(H9=0,0,I9/H9)
A10: Phase 2 | B10: Assisted Planning | C10: Sprints 10–13 | D10: 23–30 | E10: 8 | F10: Automation toggle, expanded task types, chat actions, circuit breaker, reporting. | G10: 20+ playbooks; classification accuracy > 80%. | H10: =COUNTIF('Sprint Plan'!A:A,"Phase 2") | I10: =COUNTIFS('Sprint Plan'!A:A,"Phase 2",'Sprint Plan'!J:J,"Done") | J10: =IF(H10=0,0,I10/H10)
A11: Phase 3 | B11: Supervised Autonomy | C11: Sprints 14–17 | D11: 31–38 | E11: 8 | F11: Leave-aware round-robin, multi-dev, calibration, wiki health, gap closure. | G11: Confidence measurably improving; digest rating > 75% Useful. | H11: =COUNTIF('Sprint Plan'!A:A,"Phase 3") | I11: =COUNTIFS('Sprint Plan'!A:A,"Phase 3",'Sprint Plan'!J:J,"Done") | J11: =IF(H11=0,0,I11/H11)
A12: Phase 4 | B12: Autonomous Operations | C12: Sprint 18+ | D12: 39+ (TBD) | E12: TBD | F12: Trusted tiers, auto-reply window, fine-tuning export, PM handoff. | G12: One customer fully autonomous, 0 failures over 30 days. | H12: =COUNTIF('Sprint Plan'!A:A,"Phase 4") | I12: =COUNTIFS('Sprint Plan'!A:A,"Phase 4",'Sprint Plan'!J:J,"Done") | J12: =IF(H12=0,0,I12/H12)
A13: TOTAL | E13: =SUM(E5:E9)+SUM(E10:E11) | F13: Weeks 1–38 scheduled (Phase 4 TBD). MVP exit at end of Week 22. | H13: =SUM(H5:H12) | I13: =SUM(I5:I12) | J13: =IF(H13=0,0,I13/H13)

Sheet Sprint Plan
A1: Detailed Sprint Plan — all phases, one row per deliverable
A2: Filter by Phase / Sprint / Module / Owner. Update Status to drive the Overview roll-up. Acceptance checks reference Spec v2.0 AC1–AC6.
A4: Phase | B4: Sprint | C4: Weeks | D4: Milestone | E4: Module / Workstream | F4: Deliverable | G4: Acceptance Check / Notes | H4: Owner | I4: Priority | J4: Status
A5: Phase 0 | B5: Sprint 0A | C5: 1–2 | D5: — | E5: Infrastructure | F5: Supabase project + full v2.0 schema deployed: PM core (projects, tasks, task_comments, attachments, time_logs), Desk (tickets, ticket_messages), HR schema (hr.*, 9 tables), plumbing (event_bus, notifications, notification_preferences, push_subscriptions, audit_logs) + carried-forward AI tables | G5: Schema review signed off; stubs for future phases included to avoid migration debt | H5: Dev Lead | I5: Critical | J5: Not Started
A6: Phase 0 | B6: Sprint 0A | C6: 1–2 | D6: — | E6: Infrastructure | F6: Supabase Auth wired: staff email/password + magic link, client OTP; profiles table with role enum (admin/hr/pm/developer/client) | G6: Test user per role can log in | H6: Dev | I6: Critical | J6: Not Started
A7: Phase 0 | B7: Sprint 0A | C7: 1–2 | D7: — | E7: Security | F7: RLS policies v1 on every table; hr.* policies authored separately and independently reviewed (P9, D19) | G7: RLS test suite passes per role | H7: Dev Lead | I7: Critical | J7: Not Started
A8: Phase 0 | B8: Sprint 0A | C8: 1–2 | D8: — | E8: Codebase Migration | F8: Apply §10.6 mapping to existing v0.1 repo: rename customer_projects -> projects (+ status, dedicated_developers, customer_product_id), widen classification_records.source enum to portal/email/manual/recurring, replace permissive RLS (migration 003) with full role matrix, retire api/webhooks + api/zoho + lib/zoho (keep for 1D import scripts only) | G8: Existing classification + onboarding flows still pass after migrations | H8: Dev Lead | I8: Critical | J8: Not Started
A9: Phase 0 | B9: Sprint 0A | C9: 1–2 | D9: — | E9: Pre-work | F9: Zoho API export access confirmed for Projects/Desk/People (O5) — exports scripted and tested on staging | G9: Dry-run export counts logged | H9: Admin | I9: Critical | J9: Not Started
A10: Phase 0 | B10: Sprint 0B | C10: 3–4 | D10: — | E10: Event Bus | F10: Internal event bus end-to-end: AFTER INSERT triggers on tickets/tasks -> event_bus row -> worker (pg_cron + pg_net, SKIP LOCKED) -> handler stub | G10: Dummy ticket insert produces a processed event in < 60s (replaces Zoho webhook AC) | H10: Dev | I10: Critical | J10: Not Started
A11: Phase 0 | B11: Sprint 0B | C11: 3–4 | D11: — | E11: AI Layer | F11: Vercel AI SDK + Claude API integrated; llm_config table seeded (Haiku/Sonnet per layer); llm_invocation_logs + per-customer cost attribution live from day one | G11: One logged Haiku call with tokens + cost recorded | H11: Dev | I11: High | J11: Not Started
A12: Phase 0 | B12: Sprint 0B | C12: 3–4 | D12: — | E12: Realtime | F12: Supabase Realtime enabled: Postgres Changes on tasks/tickets, Broadcast channel scheme (user:{id}, role:pm), Presence (team:attendance) — proof-of-concept hooks (D16) | G12: Live row change visible in test client < 3s | H12: Dev | I12: High | J12: Not Started
A13: Phase 0 | B13: Sprint 0B | C13: 3–4 | D13: — | E13: PWA Shell | F13: Next.js 16.2.4 App Router (extend existing v0.1 shell) + Serwist service worker + manifest; installable shell on iOS/Android/desktop; app shell layout (sidebar / top bar / bottom tabs) | G13: Install prompt works on 3 platforms | H13: Dev | I13: High | J13: Not Started
A14: Phase 0 | B14: Sprint 0B | C14: 3–4 | D14: — | E14: Email | F14: Resend account + domain verified; React Email base templates; inbound route configured (parked until Sprint 3) | G14: Test transactional email delivered | H14: Dev | I14: Medium | J14: Not Started
A15: Phase 0 | B15: Sprint 0B | C15: 3–4 | D15: — | E15: Knowledge Base | F15: LLM Wiki structure in Supabase Storage; seed Internal KB content (product how-tos, shared Sanity schemas) | G15: Internal KB browsable in admin UI | H15: PM + Dev | I15: Medium | J15: Not Started
... A83: Phase 4 | B83: Sprint 18+ | C83: 39+ (TBD) | D83: — | E83: Exit Gate | F83: Phase 4 exit: one customer at full autonomous tier, 0 failures over 30 days | G83: Mgmt review | H83: Mgmt | I83: Critical | J83: Not Started

Sheet Milestones & ACs
A1: MVP Milestones (M1–M13) and Acceptance Criteria (AC1–AC6)
A4: ID | B4: Name | C4: Scope Summary | D4: Sprint(s) | E4: Phase
A5: M1 | B5: Customer & Onboarding | C5: Customer creation, tokenized onboarding URL, dynamic forms, profile + product mapping | D5: Sprint 1 | E5: Phase 1A
A6: M2 | B6: Native Desk + Classification | C6: Portal + email-to-ticket; classification < 60s; reclassification UI | D6: Sprint 3 | E6: Phase 1A
A7: M3 | B7: Requirements Assessment | C7: CLEAR/PARTIAL/BLOCKED, clarification drafts, re-assessment on reply | D7: Sprint 6 | E7: Phase 1C
A8: M4 | B8: Daily Digest | C8: Precompiled digest_logs + ratings + HR signals for managers | D8: Sprint 6 | E8: Phase 1C
A9: M5 | B9: Plan Generation (manual) | C9: Plans with risk flags + human approval gate, structured rejections | D9: Sprint 7 | E9: Phase 1C
A10: M6 | B10: Execution + Reply | C10: Sanity / GitHub PR / MCP modes, revert, circuit breaker; Haiku replies via Resend | D10: Sprint 8 | E10: Phase 1C
A11: M7 | B11: Native Project Management | C11: Projects auto-create, Kanban/list/calendar, comments, attachments, live boards | D11: Sprints 1–2 | E11: Phase 1A
A12: M8 | B12: Time Tracking | C12: Timer + manual time_logs, PM hours queries, export | D12: Sprint 2 | E12: Phase 1A
A13: M9 | B13: Developer Dashboard | C13: Today view, team pool self-assign, hours, prompt queries | D13: Sprint 3 | E13: Phase 1A
A14: M10 | B14: LLM Wiki Seed | C14: Internal + Customer KB scaffold, seed playbooks, Wiki Lint cron, HR policy pages | D14: Sprint 7 | E14: Phase 1C
A15: M11 | B15: HR Core | C15: Directory, clock in/out (offline-queued), derived attendance, leaves + balances, timesheets, announcements, push | D15: Sprints 4–5 | E15: Phase 1B
... A18: M14 | B18: MVP Stats Page | C18: Read-only: hours by dev/project, task throughput, ticket volume + SLA, attendance summary (D25) | D18: Sprint 6 | E18: Phase 1C
A20: AC | B20: Acceptance Criterion | C20: Proven in
A21: AC1 | B21: Client submits a request from a phone via the portal; PM sees it classified in the Hub within 60 seconds. | C21: Sprint 3
A22: AC2 | B22: A CONTENT_UPDATE completes classify -> plan -> approve -> execute -> client reply without leaving the Hub. | C22: Sprint 8
A23: AC3 | B23: Developer self-assigns from the team pool; PM gets a realtime notification; hours appear in PM hours view. | C23: Sprint 3
A24: AC4 | B24: Employee clocks in on mobile, files a half-day leave, gets approval — balance, calendar, and pool update automatically. | C24: Sprint 5
A25: AC5 | B25: Full payroll-period timesheet export produced from Hub data with zero reference to Zoho. | C25: Sprint 5
A26: AC6 | B26: PM asks the chat 'what are today's priority tasks, and who is absent?' and gets an accurate, RLS-scoped answer with links. | C26: Sprint 8
A27: AC7 | B27: PM clicks 'Publish to dev' on a completed content task; dev URL appears on the task and in the drafted client reply (US-PUB-1). | C27: Sprint 8

Sheet Timeline
A1: Timeline — Weeks 1–38 (Phase 4 TBD)
A2: One row per sprint; colored cells = active weeks. MVP exit marker at Week 22.
A4: Sprint | B4: Focus | C4: 1 | D4: 2 | E4: 3 | F4: 4 | G4: 5 | H4: 6 | I4: 7 | J4: 8 | K4: 9 | L4: 10 | M4: 11 | N4: 12 | O4: 13 | P4: 14 | Q4: 15 | R4: 16 | S4: 17 | T4: 18 | U4: 19 | V4: 20 | W4: 21 | X4: 22 | Y4: 23 | Z4: 24 | AA4: 25 | AB4: 26 | AC4: 27 | AD4: 28 | AE4: 29 | AF4: 30 | AG4: 31 | AH4: 32 | AI4: 33 | AJ4: 34 | AK4: 35 | AL4: 36 | AM4: 37 | AN4: 38
A5: Sprint 0A | B5: Schema + auth + RLS + codebase mapping
A6: Sprint 0B | B6: Event bus + realtime + PWA + Resend + KB
A7: Sprint 1 | B7: Onboarding + customer hub (M1)
A8: Sprint 2 | B8: Native PM + time tracking (M7, M8)
A9: Sprint 3 | B9: Desk + classification + dev dashboard (M2, M9)
A10: Sprint 4 | B10: Directory + attendance + announcements (M11)
A11: Sprint 5 | B11: Leaves + timesheets + push (M11)
A12: Sprint 6 | B12: Assessment + digest + stats page (M3, M4, M14)
A13: Sprint 7 | B13: Plans + Ops Chat v1 + KB seed (M5, M13, M10)
A14: Sprint 8 | B14: Execution + publish flow + reply + chat complete (M6, M13)
A15: Sprint 9 | B15: Zoho migration + training + MVP exit (M12)
A16: Sprint 10 | B16: Automation toggle + new task types
... A23: Sprint 17 | B23: Gap closure + Phase 3 exit
B25: Legend: | C25: 0 | E25: 1A | G25: 1B | I25: 1C | K25: 1D | M25: 2 | O25: 3 | Q25: Week 22 = MVP exit (red header)

Sheet Open Items
A1: Open Items — must-resolve-by sprint gates
A4: # | B4: Item | C4: Owner | D4: Priority | E4: Resolve before | F4: Status
A5: O1 | B5: Final Task Type Taxonomy incl. HR_REQUEST sub-types | C5: PM + HR | D5: HIGH | E5: Sprint 3 | F5: Open
A6: O2 | B6: Leave accrual rules + opening balance sign-off (per employee) | C6: HR | D6: HIGH | E6: Sprint 5 | F6: Open
A7: O3 | B7: Attendance policy: grace period, geolocation on/off, correction window | C7: HR + Mgmt | D7: HIGH | E7: Sprint 4 | F7: Open
A8: O4 | B8: Support email address + Resend Inbound domain setup | C8: Dev | D8: HIGH | E8: Sprint 3 | F8: Open
A9: O5 | B9: Zoho API export access for all five products (before licenses lapse) | C9: Admin | D9: HIGH | E9: Sprint 0A | F9: Open
A10: O6 | B10: SLA matrix per priority for the Desk | C10: PM | D10: MEDIUM | E10: Sprint 3 | F10: Open
A11: O7 | B11: Notification preference defaults per role | C11: PM | D11: MEDIUM | E11: Sprint 3 | F11: Open
A12: O8 | B12: PH holiday calendar 2026–2027 seed data | C12: HR | D12: MEDIUM | E12: Sprint 4 | F12: Open
A13: O9 | B13: Client portal auth mode: magic link only vs optional password | C13: PM | D13: MEDIUM | E13: Sprint 3 | F13: Open
A14: O10 | B14: 1B/1C parallel workstreams vs sequential (staffing) | C14: Mgmt | D14: MEDIUM | E14: Before Sprint 4 | F14: Open
A15: O11 | B15: Round-robin load threshold defaults | C15: PM | D15: MEDIUM | E15: Sprint 14 | F15: Open
A16: O12 | B16: Zoho -> Hub task status & priority mapping table reviewed + signed off by PM before migration dry run (data fidelity) | C16: PM | D16: HIGH | E16: Sprint 9 | F16: Open
